LICENSE
MANIFEST.in
README.md
setup.cfg
setup.py
PyContact/__init__.py
PyContact/pycontact.py
PyContact/core/Biochemistry.py
PyContact/core/ContactAnalyzer.py
PyContact/core/ContactFilters.py
PyContact/core/DataHandler.py
PyContact/core/LoadConfiguration.py
PyContact/core/LogPool.py
PyContact/core/Scripting.py
PyContact/core/__init__.py
PyContact/core/aroundPatch.py
PyContact/core/multi_trajectory.py
PyContact/cy_modules/__init__.py
PyContact/cy_modules/cy_gridsearch.cpp
PyContact/cy_modules/cy_gridsearch.pyx
PyContact/cy_modules/src/ResizeArray.h
PyContact/cy_modules/src/gridsearch.C
PyContact/cy_modules/src/vmdstream.h
PyContact/db/DbReader.py
PyContact/db/__init__.py
PyContact/db/aa.db
PyContact/exampleData/__init__.py
PyContact/exampleData/datafiles.py
PyContact/exampleData/defaultsession
PyContact/exampleData/md.tpr
PyContact/exampleData/md_noPBC.xtc
PyContact/exampleData/rpn11_ubq.dcd
PyContact/exampleData/rpn11_ubq.psf
PyContact/gui/Canvas.py
PyContact/gui/DetailWidget.py
PyContact/gui/Dialogues.py
PyContact/gui/ErrorBox.py
PyContact/gui/ErrorMessages.py
PyContact/gui/ExportTabWidget.py
PyContact/gui/HelpButton.py
PyContact/gui/LabelView.py
PyContact/gui/MainQtGui.py
PyContact/gui/MainWindow.py
PyContact/gui/MoleculeTracker.py
PyContact/gui/Plotters.py
PyContact/gui/Preferences.py
PyContact/gui/SasaWidgets.py
PyContact/gui/Statistics.py
PyContact/gui/TableModels.py
PyContact/gui/TrackCanvas.py
PyContact/gui/VMDControlPanel.py
PyContact/gui/__init__.py
PyContact/gui/detail_ui.py
PyContact/gui/remote_ctl.tcl
PyContact/gui/sasa_gui.py
PyContact/gui/statistics_ui.py
PyContact/gui/track_mol_gui.py
pycontact.egg-info/PKG-INFO
pycontact.egg-info/SOURCES.txt
pycontact.egg-info/dependency_links.txt
pycontact.egg-info/entry_points.txt
pycontact.egg-info/requires.txt
pycontact.egg-info/top_level.txt
tests/__init__.py
tests/map_animate.py
tests/test_basic.py