Metadata-Version: 1.1
Name: pycontact
Version: 1.0.4
Summary: PyContact
Home-page: https://github.com/maxscheurer/pycontact
Author: Maximilian Scheurer, Peter Rodenkirch
Author-email: mscheurer@ks.uiuc.edu
License: GPLv3
Keywords: computational biophysics simulation biology bioinformatics visualization protein biomolecules dna
Platform: UNKNOWN
Classifier: Development Status :: 5 - Production/Stable
Classifier: Intended Audience :: Science/Research
Classifier: Topic :: Scientific/Engineering
Classifier: License :: OSI Approved :: GNU General Public License v3 (GPLv3)
Classifier: Programming Language :: Python :: 2.7
Classifier: Programming Language :: Python :: 3.6
